src/noteshrunk.py
noteshrunk-1.6.0.dist-info/METADATA
noteshrunk-1.6.0.dist-info/WHEEL
noteshrunk-1.6.0.dist-info/entry_points.txt
noteshrunk-1.6.0.dist-info/licenses/LICENSE
noteshrunk-1.6.0.dist-info/RECORD
