Metadata-Version: 2.3
Name: noteshrunk
Version: 1.6.0
Summary: Document Color Palette Compression
Project-URL: Homepage, https://github.com/suuuehgi/noteshrunk
Project-URL: Issues, https://github.com/suuuehgi/noteshrunk/issues
Author: suuuehgi
License:                     GNU GENERAL PUBLIC LICENSE
License-File: LICENSE
Classifier: Intended Audience :: Developers
Classifier: License :: OSI Approved :: GNU General Public License v3 or later (GPLv3+)
Classifier: Programming Language :: Python :: 3
Requires-Python: >=3.9
Requires-Dist: argcomplete
Requires-Dist: numpy
Requires-Dist: pillow
Requires-Dist: scikit-image
Requires-Dist: scikit-learn
Requires-Dist: scipy
